xawsprofile/__init__.py
xawsprofile/__main__.py
xawsprofile/aws.py
xawsprofile/cli.py
xawsprofile-0.3.5.dist-info/entry_points.txt
xawsprofile-0.3.5.dist-info/LICENSE
xawsprofile-0.3.5.dist-info/WHEEL
xawsprofile-0.3.5.dist-info/METADATA
xawsprofile-0.3.5.dist-info/RECORD
