Metadata-Version: 2.1
Name: xawsprofile
Version: 0.3.5
Summary: AWS profile utility
License: MIT
Author: Daniel Clayton
Author-email: dclayton@godaddy.com
Requires-Python: >=3.7,<4
Classifier: License :: OSI Approved :: MIT License
Classifier: Programming Language :: Python :: 3
Classifier: Programming Language :: Python :: 3.10
Classifier: Programming Language :: Python :: 3.7
Classifier: Programming Language :: Python :: 3.8
Classifier: Programming Language :: Python :: 3.9
Requires-Dist: boto3 (>=1.20.33,<2.0.0)
Requires-Dist: click (>=8.1.0)
